s3table/__init__.py
s3table/catalog.py
s3table/cli.py
s3table/table.py
s3table-0.0.2.dist-info/LICENSE
s3table-0.0.2.dist-info/LICENSE copy
s3table-0.0.2.dist-info/METADATA
s3table-0.0.2.dist-info/WHEEL
s3table-0.0.2.dist-info/RECORD
